{
	"sw08necromancerZombie" : {
		"name" : {
			"singular" : "Zombie",
			"plural" : "Zombies"
		},
		"faction" : "swsw08necromancerfaction",
		"level" : 2,
		"cost" : {
			"gold" : 105
		},
		"speed" : 3,
		"hitPoints" : 15,
		"shots" : 0,
		"attack" : 5,
		"defense" : 2,
		"damage" : {
			"min" : 2,
			"max" : 3
		},
		"fightValue" : 143,
		"aiValue" : 135,
		"advMapAmount" : {
			"min" : 15,
			"max" : 30
		},
		"growth" : 9,
		"horde" : 0,
		"hasDoubleWeek" : true,
		"doubleWide" : false,
		"upgrades" : ["sw08necromancerMutantZombie"],
		"abilities" : {
			"ability1" : {
				"type" : "UNDEAD"
			}
		},
		"graphics" : {
			"iconSmall" : "sw08necromancer-creatures/cprsmall.def:60",
			"iconLarge" : "sw08necromancer-creatures/TWCRPORT.def:60",
			"map" : "sw08necromancer-creatures/map/AVWzomb0",
			"animation" : "sw08necromancer-creatures/battle/c058zomb",
			"timeBetweenFidgets" : 1,
			"animationTime" : {
				"idle" : 10,
				"walk" : 1,
				"attack" : 1
			},
			"missile" : {
				"projectile" : "sw08necromancer-creatures/battle/PLCBOWX",
				"offset" : {
					"upperX" : 41,
					"upperY" : -92,
					"middleX" : 58,
					"middleY" : -79,
					"lowerX" : 29,
					"lowerY" : -14
				},
				"frameAngles" : [90, 72, 45, 27, 0, -27, -45, -72, -90, 0, 0, 0],
				"attackClimaxFrame" : 10
			}
		},
		"sound" : {
			"attack" : "sw08necromancer/zombie/ZOMBATTK.wav",
			"defend" : "sw08necromancer/zombie/ZOMBDFND.wav",
			"killed" : "sw08necromancer/zombie/ZOMBKILL.wav",
			"move" : "sw08necromancer/zombie/ZOMBMOVE.wav",
			"wince" : "sw08necromancer/zombie/ZOMBWNCE.wav"
			// "shoot" :""
		}
	}
}
