{
	"sw08Evilla": {
		"female": true,
		"class": "swswWarlock",
		"texts": {
			"name": "Evilla",
			"biography": "The past of this person is covered in shroud.",
			"specialty": {
				"name": "Curse",
				"description": "Curse",
				"tooltip": "Casts Curse with increased effect, based on hero level compared to the level of the target unit (the bonus is greater when used on weaker units)."
			}
		},
		"images": {
			"specialtySmall": "swWarlockHeroes/UN32.def:94",
			"specialtyLarge": "swWarlockHeroes/UN44.def:94",
			"large": "swWarlockHeroes/port/HPL048HR.png",
			"small": "swWarlockHeroes/port/HPS048HR.png"
		},
		"spellbook": [
			"curse"
		],
		"army": [
			{
				"creature": "swWarlockCentaur",
				"min": 6,
				"max": 9
			},
			{
				"creature": "swWarlockGargoyle",
				"min": 6,
				"max": 8
			},
			{
				"creature": "swWarlockGriffin",
				"min": 2,
				"max": 3
			}
		],
		"skills": [
			{
				"skill": "wisdom",
				"level": "basic"
			},
			{
				"skill": "resistance",
				"level": "basic"
			}
		],
		"specialty": {
			"bonuses": {
				"ability1": {
					"type": "SPELL",
					"val": 3,
					"valueType": "INDEPENDENT_MAX",
					"subtype": "spell.curse"
				}
			}
		}
	}
}