{
	"sw08Tumur": {
		"female": false,
		"class": "swswOasis",
		"texts": {
			"name": "Tumur",
			"biography": "no bio yet",
			"specialty": {
				"name": "Offense",
				"description": "Offense",
				"tooltip": "Receives a 5% per level bonus to Offense skill percentage."
			}
		},
		"images": {
			"specialtySmall": "swOasisHeroes/UN32.def:141",
			"specialtyLarge": "swOasisHeroes/UN44.def:141",
			"large": "swOasisHeroes/port/HPL005EL",
			"small": "swOasisHeroes/port/HPS005EL"
		},
		"spellbook": [],
		"army": [
			{
				"creature": "swOasisRogue",
				"min": 8,
				"max": 16
			},
			{
				"creature": "swOasisNomad",
				"min": 2,
				"max": 3
			},
			{
				"creature": "swOasisNomad",
				"min": 2,
				"max": 3
			}
		],
		"skills": [
			{
				"skill": "pathfinding",
				"level": "basic"
			},
			{
				"skill": "offence",
				"level": "basic"
			}
		],
		"specialty": {
			"bonuses": {
				"ability1": {
					"type": "PERCENTAGE_DAMAGE_BOOST",
					"subtype": "damageTypeMelee",
					"valueType": "ADDITIVE_VALUE",
					"val": 5,
					"updater": "TIMES_HERO_LEVEL"
				}
			}
		}
	}
}